turkleton-1.2.1.dist-info/metadata.json
turkleton-1.2.1.dist-info/WHEEL
turkleton-1.2.1.dist-info/top_level.txt
turkleton-1.2.1.dist-info/METADATA
turkleton-1.2.1.dist-info/RECORD
turkleton-1.2.1.dist-info/DESCRIPTION.rst
turkleton/__init__.py
turkleton/connection.py
turkleton/utils.py
turkleton/errors.py
turkleton/assignment/__init__.py
turkleton/assignment/assignment.py
turkleton/assignment/task.py
turkleton/assignment/hit.py
turkleton/assignment/answer.py
