Metadata-Version: 2.0
Name: turkleton
Version: 1.2.1
Summary: Simplified interfaces for assignments on Mechanical Turk.
Home-page: https://github.com/etscrivner/turkleton
Author: Eric Scrivner
Author-email: eric.t.scrivner@gmail.com
License: BSD
Keywords: turkleton
Platform: UNKNOWN
Classifier: Development Status :: 5 - Production/Stable
Classifier: Intended Audience :: Developers
Classifier: License :: OSI Approved :: BSD License
Classifier: Natural Language :: English
Classifier: Programming Language :: Python :: 2
Classifier: Programming Language :: Python :: 2.7
Classifier: Programming Language :: Python :: 3
Classifier: Programming Language :: Python :: 3.3
Classifier: Programming Language :: Python :: 3.4
Requires-Dist: boto
Requires-Dist: six
